<page>
  <controls count="1">
    <control type="DivRoot" pathname="/divRoot">
      <backgroundColor>FFFFFF</backgroundColor>
      <bgColorEnabled>true</bgColorEnabled>
      <dockX>fill</dockX>
      <dockY>fill</dockY>
      <height>799</height>
      <left>0</left>
      <top>0</top>
      <width>1045</width>
    </control>
  </controls>
  <taskSet count="1">
    <taskSetItem name="listenings">
      <script1 />
      <script2>
sql = "select orderid from ujia_order where id = '1'"; 
sqlResult=db.executeQuery("UJ", sql);
db.read(sqlResult);    
var name = db.getString(sqlResult,"orderid");
eio.appendString8(name);
//订单表

</script2>
      <script3 />
    </taskSetItem>
  </taskSet>
  <gridLines count="0" />
</page>